src/__init__.py
src/gclfs/__init__.py
src/gclfs/main.py
src/gclfs/commands/__init__.py
src/gclfs/commands/commands.py
src/gclfs/core/__init__.py
src/gclfs/core/strings.py
src/gclfs/storage/__init__.py
src/gclfs/storage/s3.py
src/gclfs/storage/sync.py
gclfs-0.1.1.dist-info/LICENSE.md
gclfs-0.1.1.dist-info/METADATA
gclfs-0.1.1.dist-info/WHEEL
gclfs-0.1.1.dist-info/entry_points.txt
gclfs-0.1.1.dist-info/top_level.txt
gclfs-0.1.1.dist-info/RECORD
