Metadata-Version: 2.1
Name: gclfs
Version: 0.1.1
Summary: Git LFS for large files that need cloud storage.
Home-page: https://github.com/mjlabe/gclfs
Author: Marc LaBelle
License: MIT
Keywords: GIT,LFS,CLOUD,STORAGE,AWS,S3
Classifier: Development Status :: 3 - Alpha
Classifier: License :: OSI Approved :: MIT License
Classifier: Programming Language :: Python :: 3.9
Requires-Python: >=3.6, <4
License-File: LICENSE.md
Requires-Dist: boto3 (<=2,>=1)
Requires-Dist: click (<=9,>=8)
